unxt_hypothesis/__init__.py
unxt_hypothesis/_version.py
unxt_hypothesis/py.typed
unxt_hypothesis/_src/__init__.py
unxt_hypothesis/_src/dimensions.py
unxt_hypothesis/_src/quantities.py
unxt_hypothesis/_src/units.py
unxt_hypothesis/_src/unitsystems.py
unxt_hypothesis-1.10.1.dist-info/METADATA
unxt_hypothesis-1.10.1.dist-info/WHEEL
unxt_hypothesis-1.10.1.dist-info/RECORD
