Metadata-Version: 2.4
Name: unxt-hypothesis
Version: 1.10.1
Summary: Hypothesis strategies for unxt
Project-URL: Bug Tracker, https://github.com/GalacticDynamics/unxt/issues
Project-URL: Homepage, https://github.com/GalacticDynamics/unxt
Author-email: GalacticDynamics <nstarman@users.noreply.github.com>, Nathaniel Starkman <nstarman@users.noreply.github.com>
License: BSD-3-Clause
Classifier: Development Status :: 3 - Alpha
Classifier: Intended Audience :: Developers
Classifier: Intended Audience :: Science/Research
Classifier: License :: OSI Approved :: BSD License
Classifier: Operating System :: OS Independent
Classifier: Programming Language :: Python
Classifier: Programming Language :: Python :: 3
Classifier: Programming Language :: Python :: 3 :: Only
Classifier: Programming Language :: Python :: 3.11
Classifier: Programming Language :: Python :: 3.12
Classifier: Programming Language :: Python :: 3.13
Classifier: Topic :: Scientific/Engineering
Classifier: Typing :: Typed
Requires-Python: >=3.11
Requires-Dist: hypothesis[numpy]>=6.138.14
Requires-Dist: jax>=0.5.3
Requires-Dist: unxt
